<?xml version="1.0" encoding="utf-8" ?>
<settings>
  <entry key="key1" value="value1" type="String"/>
  <entry key="key2" value="value2" type="String"/>
  <entry key="key3" value="21" type="Int16"/>

  <!-- LUI settings -->
  <entry key="lui:datasetOldComponentsSet" value="19266" type="int"/>
  <entry key="lui:datastructureOldComponentsSet" value="663" type="int"/>

  <entry key="lui:datasetNewComponentsSet" value="25086" type="int"/>
  <entry key="lui:datastructureNewComponentsSet" value="1056" type="int"/>

  <entry key="lui:years:min" value="2006" type="int" />
  <entry key="lui:years:max" value="2020" type="int" />
  <entry key="lui:filename:download" value="LUI" type="string" />
  <entry key="lui:filename:namespace" value="LUI" type="string" />

  <entry key="lui:msg:alb" type="string" value="" />
  <entry key="lui:msg:hai" type="string" value="" />
  <entry key="lui:msg:sch" type="string" value="" />

  <entry key="lui:epPlotsDataset" value="20826" type="int"/>
  <entry key="lui:lanuDataset" value="26487" type="int"/>

</settings>
